setup.py
hongchaseeing/__init__.py
hongchaseeing/hongchaseeing.py
hongchaseeing/main.py
hongchaseeing.egg-info/PKG-INFO
hongchaseeing.egg-info/SOURCES.txt
hongchaseeing.egg-info/dependency_links.txt
hongchaseeing.egg-info/top_level.txt