Metadata-Version: 1.1
Name: hongchaseeing
Version: 0.1.1
Summary: 看这是什么：“”，没错，这是一个关于字符串的库！！！
Home-page: https://github.com/
Author: haowen zhang
Author-email: 806670753@qq.com
License: UNKNOWN
Platform: UNKNOWN
Classifier: Programming Language :: Python :: 3
Classifier: License :: OSI Approved :: MIT License
Classifier: Operating System :: OS Independent
